fastcov.py
fastcov-1.16.data/scripts/fastcov
fastcov-1.16.data/scripts/fastcov_summary
fastcov-1.16.data/scripts/fastcov_to_sonarqube
fastcov-1.16.dist-info/LICENSE
fastcov-1.16.dist-info/METADATA
fastcov-1.16.dist-info/WHEEL
fastcov-1.16.dist-info/top_level.txt
fastcov-1.16.dist-info/RECORD
