Metadata-Version: 2.1
Name: fastcov
Version: 1.16
Summary: A massively parallel gcov wrapper for generating intermediate coverage formats fast
Home-page: https://github.com/RPGillespie6/fastcov
Author: Bryan Gillespie
Author-email: rpgillespie6@gmail.com
License: mit
Platform: any
Classifier: Development Status :: 5 - Production/Stable
Classifier: Topic :: Utilities
Classifier: Programming Language :: Python :: 3
Classifier: Programming Language :: Python :: 3 :: Only
Classifier: Programming Language :: Python :: 3.5
Classifier: Programming Language :: Python :: 3.6
Classifier: Programming Language :: Python :: 3.7
Classifier: Environment :: Console
Classifier: Intended Audience :: Developers
Classifier: License :: OSI Approved :: MIT License
Classifier: Operating System :: POSIX :: Linux
Classifier: Operating System :: Unix
Classifier: Operating System :: MacOS
Classifier: Operating System :: Microsoft :: Windows
Requires-Python: >=3.5
License-File: LICENSE
